test_my_binding/__init__.py
test_my_binding/booleans.py
test_my_binding/intersections.py
test_my_binding/measure.py
test_my_binding/meshing.py
test_my_binding/reconstruction.py
test_my_binding/skeletonization.py
test_my_binding/slicer.py
test_my_binding/straight_skeleton_2.py
test_my_binding/subdivision.py
test_my_binding/test_my_binding_ext.cpython-311-x86_64-linux-gnu.so
test_my_binding/triangulation.py
test_my_binding/types.py
test_my_binding-1.0.89.dist-info/METADATA
test_my_binding-1.0.89.dist-info/WHEEL
test_my_binding-1.0.89.dist-info/RECORD
test_my_binding-1.0.89.dist-info/licenses/LICENSE
