Metadata-Version: 2.1
Name: test_my_binding
Version: 1.0.89
Summary: CGAL wrapper for COMPAS.
Author-Email: tom van mele <tom.v.mele@gmail.com>, Petras Vestartas <petrasvestartas@gmail.com>
Classifier: License :: OSI Approved :: GNU Lesser General Public License v3 (LGPLv3)
Classifier: Programming Language :: Python :: 3.9
Classifier: Programming Language :: Python :: Implementation :: CPython
Classifier: Development Status :: 4 - Beta
Project-URL: Homepage, https://github.com/compas-dev/test_my_binding
Requires-Python: >=3.9
Requires-Dist: numpy
Requires-Dist: compas
